natsort/__init__.py
natsort/__main__.py
natsort/natsort.py
natsort/ns_enum.py
natsort/py.typed
natsort/unicode_numbers.py
natsort/unicode_numeric_hex.py
natsort/utils.py
natsort/compat/__init__.py
natsort/compat/fake_fastnumbers.py
natsort/compat/fastnumbers.py
natsort/compat/locale.py
natsort-8.3.1.dist-info/LICENSE
natsort-8.3.1.dist-info/METADATA
natsort-8.3.1.dist-info/WHEEL
natsort-8.3.1.dist-info/entry_points.txt
natsort-8.3.1.dist-info/top_level.txt
natsort-8.3.1.dist-info/RECORD
