Metadata-Version: 2.1
Name: natsort
Version: 8.3.1
Summary: Simple yet flexible natural sorting in Python.
Home-page: https://github.com/SethMMorton/natsort
Author: Seth M. Morton
Author-email: drtuba78@gmail.com
License: MIT
Platform: UNKNOWN
Classifier: Development Status :: 5 - Production/Stable
Classifier: Intended Audience :: Developers
Classifier: Intended Audience :: Science/Research
Classifier: Intended Audience :: System Administrators
Classifier: Intended Audience :: Information Technology
Classifier: Intended Audience :: Financial and Insurance Industry
Classifier: Operating System :: OS Independent
Classifier: License :: OSI Approved :: MIT License
Classifier: Natural Language :: English
Classifier: Programming Language :: Python
Classifier: Programming Language :: Python :: 3
Classifier: Programming Language :: Python :: 3.7
Classifier: Programming Language :: Python :: 3.8
Classifier: Programming Language :: Python :: 3.9
Classifier: Programming Language :: Python :: 3.10
Classifier: Programming Language :: Python :: 3.11
Classifier: Topic :: Scientific/Engineering :: Information Analysis
Classifier: Topic :: Utilities
Classifier: Topic :: Text Processing
Requires-Python: >=3.7
Provides-Extra: fast
Provides-Extra: icu
License-File: LICENSE
